python/__init__.py
python/error_codes.py
python/test.py
central_error_code-1.0.3.dist-info/METADATA
central_error_code-1.0.3.dist-info/WHEEL
central_error_code-1.0.3.dist-info/top_level.txt
central_error_code-1.0.3.dist-info/RECORD
