Metadata-Version: 2.2
Name: central-error-code
Version: 1.0.3
Summary: A module to handle error codes loaded from JSON files
Author: Your Name
Author-email: your.email@example.com
Classifier: Programming Language :: Python :: 3
Classifier: License :: OSI Approved :: MIT License
Classifier: Operating System :: OS Independent
Dynamic: author
Dynamic: author-email
Dynamic: classifier
Dynamic: summary
